{
  "type": "UploadedFiles",
  "managed": false,
  "formatType": "json",
  "checklists": {
    "checklists": []
  },
  "customMeta": {
    "kv": {}
  },
  "flowOptions": {
    "virtualizable": false,
    "rebuildBehavior": "NORMAL",
    "crossProjectBuildBehavior": "DEFAULT"
  },
  "readWriteOptions": {
    "preserveOrder": false,
    "writeBuckets": 1,
    "forceSingleOutputFile": false,
    "defaultReadOrdering": {
      "enabled": false,
      "rules": []
    }
  },
  "formatParams": {
    "maxExpansionDepth": -1,
    "nestedArraysHandling": "PRESERVE",
    "extractFromSingleElement": false,
    "nestedArraysMaxElements": 100,
    "nestedArraysMaxContentSize": 300000,
    "headerRow": false
  },
  "partitioning": {
    "ignoreNonMatchingFile": false,
    "considerMissingRequestedPartitionsAsEmpty": false,
    "dimensions": []
  },
  "versionTag": {
    "versionNumber": 1,
    "lastModifiedBy": {
      "login": "admin"
    },
    "lastModifiedOn": 1609064353665
  },
  "creationTag": {
    "versionNumber": 0,
    "lastModifiedBy": {
      "login": "admin"
    },
    "lastModifiedOn": 1609064353603
  },
  "tags": [],
  "params": {
    "uploadConnection": "Default (in DSS data dir.)",
    "notReadyIfEmpty": false,
    "filesSelectionRules": {
      "mode": "ALL",
      "excludeRules": [],
      "includeRules": [],
      "explicitFiles": []
    }
  },
  "schema": {
    "columns": [
      {
        "name": "group_matched",
        "type": "string"
      },
      {
        "name": "badges",
        "type": "string"
      },
      {
        "name": "distance_mi",
        "type": "string"
      },
      {
        "name": "content_hash",
        "type": "string"
      },
      {
        "name": "common_friends",
        "type": "string"
      },
      {
        "name": "common_likes",
        "type": "string"
      },
      {
        "name": "common_friend_count",
        "type": "string"
      },
      {
        "name": "common_like_count",
        "type": "string"
      },
      {
        "name": "connection_count",
        "type": "string"
      },
      {
        "name": "_id",
        "type": "string"
      },
      {
        "name": "bio",
        "type": "string"
      },
      {
        "name": "birth_date",
        "type": "string"
      },
      {
        "name": "name",
        "type": "string"
      },
      {
        "name": "ping_time",
        "type": "string"
      },
      {
        "name": "photos",
        "type": "string"
      },
      {
        "name": "jobs",
        "type": "string"
      },
      {
        "name": "schools",
        "type": "string"
      },
      {
        "name": "teaser.string",
        "type": "string"
      },
      {
        "name": "teasers",
        "type": "string"
      },
      {
        "name": "gender",
        "type": "string"
      },
      {
        "name": "birth_date_info",
        "type": "string"
      },
      {
        "name": "s_number",
        "type": "string"
      },
      {
        "name": "show_gender_on_profile",
        "type": "string"
      },
      {
        "name": "teaser.type",
        "type": "string"
      },
      {
        "name": "hide_age",
        "type": "string"
      },
      {
        "name": "hide_distance",
        "type": "string"
      },
      {
        "name": "is_traveling",
        "type": "string"
      },
      {
        "name": "instagram.last_fetch_time",
        "type": "string"
      },
      {
        "name": "instagram.completed_initial_fetch",
        "type": "string"
      },
      {
        "name": "instagram.photos",
        "type": "string"
      },
      {
        "name": "instagram.media_count",
        "type": "string"
      },
      {
        "name": "instagram.username",
        "type": "string"
      },
      {
        "name": "spotify_theme_track.id",
        "type": "string"
      },
      {
        "name": "spotify_theme_track.name",
        "type": "string"
      },
      {
        "name": "spotify_theme_track.album.id",
        "type": "string"
      },
      {
        "name": "spotify_theme_track.album.name",
        "type": "string"
      },
      {
        "name": "spotify_theme_track.album.images",
        "type": "string"
      },
      {
        "name": "spotify_theme_track.artists",
        "type": "string"
      },
      {
        "name": "spotify_theme_track.preview_url",
        "type": "string"
      },
      {
        "name": "spotify_theme_track.uri",
        "type": "string"
      },
      {
        "name": "instagram.profile_picture",
        "type": "string"
      },
      {
        "name": "spotify_top_artists",
        "type": "string"
      }
    ],
    "userModified": true
  },
  "metrics": {
    "probes": [
      {
        "type": "basic",
        "enabled": true,
        "computeOnBuildMode": "PARTITION",
        "meta": {
          "name": "Basic data",
          "level": 0
        },
        "configuration": {}
      },
      {
        "type": "records",
        "enabled": true,
        "computeOnBuildMode": "NO",
        "meta": {
          "name": "Record count",
          "level": 0
        },
        "configuration": {}
      }
    ],
    "engineConfig": {
      "padRunsWithMetrics": false,
      "hive": {
        "active": true,
        "extraConf": []
      },
      "basic": {},
      "dss": {
        "active": true,
        "selection": {
          "useMemTable": false,
          "filter": {
            "distinct": false,
            "enabled": false
          },
          "partitionSelectionMethod": "ALL",
          "latestPartitionsN": 1,
          "ordering": {
            "enabled": false,
            "rules": []
          },
          "samplingMethod": "FULL",
          "maxRecords": -1,
          "targetRatio": 0.02,
          "withinFirstN": -1,
          "maxReadUncompressedBytes": -1
        }
      },
      "sql": {
        "active": true
      },
      "impala": {
        "active": true
      },
      "spark": {
        "active": true,
        "extraConf": []
      },
      "python": {}
    },
    "displayedState": {
      "columns": [],
      "metrics": [
        "basic:COUNT_COLUMNS",
        "basic:COUNT_FILES",
        "basic:SIZE",
        "records:COUNT_RECORDS"
      ]
    }
  },
  "metricsChecks": {
    "runOnBuild": false,
    "checks": [],
    "displayedState": {
      "checks": []
    }
  },
  "customFields": {}
}